PicoRobotics.py
KitronikPicoRobotics-1.0.0.dist-info/LICENSE
KitronikPicoRobotics-1.0.0.dist-info/METADATA
KitronikPicoRobotics-1.0.0.dist-info/WHEEL
KitronikPicoRobotics-1.0.0.dist-info/top_level.txt
KitronikPicoRobotics-1.0.0.dist-info/RECORD
