Metadata-Version: 2.1
Name: KitronikPicoRobotics
Version: 1.0.0
Summary: Kitronik Robotics Board for Raspberry Pi Pico to drive 4 motors (or 2 stepper motors) and 8 servos
License-File: LICENSE
